libsbne/__init__.py
libsbne/_libsbne.pyd
libsbne/cdt.dll
libsbne/cgraph.dll
libsbne/concrt140.dll
libsbne/config6
libsbne/expat.dll
libsbne/gvc.dll
libsbne/gvplugin_neato_layout.dll
libsbne/gvplugin_pango.dll
libsbne/libsbml.dll
libsbne/msvcp140.dll
libsbne/msvcp140_1.dll
libsbne/msvcp140_2.dll
libsbne/msvcp140_atomic_wait.dll
libsbne/msvcp140_codecvt_ids.dll
libsbne/pathplan.dll
libsbne/vcruntime140.dll
libsbne/vcruntime140_1.dll
libsbne/xdot.dll
libsbne-0.0.6.dist-info/METADATA
libsbne-0.0.6.dist-info/WHEEL
libsbne-0.0.6.dist-info/top_level.txt
libsbne-0.0.6.dist-info/RECORD
